jupyter_contrib_nbextensions/__init__.py
jupyter_contrib_nbextensions/application.py
jupyter_contrib_nbextensions/install.py
jupyter_contrib_nbextensions/migrate.py
jupyter_contrib_nbextensions/config_scripts/__init__.py
jupyter_contrib_nbextensions/config_scripts/highlight_html_cfg.py
jupyter_contrib_nbextensions/config_scripts/highlight_latex_cfg.py
jupyter_contrib_nbextensions/nbconvert_support/__init__.py
jupyter_contrib_nbextensions/nbconvert_support/collapsible_headings.py
jupyter_contrib_nbextensions/nbconvert_support/embedhtml.py
jupyter_contrib_nbextensions/nbconvert_support/execute_time.py
jupyter_contrib_nbextensions/nbconvert_support/exporter_inliner.py
jupyter_contrib_nbextensions/nbconvert_support/js_highlight.py
jupyter_contrib_nbextensions/nbconvert_support/nbTranslate.py
jupyter_contrib_nbextensions/nbconvert_support/pp_highlighter.py
jupyter_contrib_nbextensions/nbconvert_support/pre_codefolding.py
jupyter_contrib_nbextensions/nbconvert_support/pre_embedimages.py
jupyter_contrib_nbextensions/nbconvert_support/pre_pymarkdown.py
jupyter_contrib_nbextensions/nbconvert_support/pre_svg2pdf.py
jupyter_contrib_nbextensions/nbconvert_support/toc2.py
jupyter_contrib_nbextensions/nbextensions/addbefore/addbefore.yaml
jupyter_contrib_nbextensions/nbextensions/addbefore/icon.png
jupyter_contrib_nbextensions/nbextensions/addbefore/main.js
jupyter_contrib_nbextensions/nbextensions/addbefore/readme.md
jupyter_contrib_nbextensions/nbextensions/autosavetime/README.md
jupyter_contrib_nbextensions/nbextensions/autosavetime/autosavetime.yaml
jupyter_contrib_nbextensions/nbextensions/autosavetime/icon.png
jupyter_contrib_nbextensions/nbextensions/autosavetime/main.js
jupyter_contrib_nbextensions/nbextensions/autoscroll/README.md
jupyter_contrib_nbextensions/nbextensions/autoscroll/autoscroll.yaml
jupyter_contrib_nbextensions/nbextensions/autoscroll/icon.png
jupyter_contrib_nbextensions/nbextensions/autoscroll/main.js
jupyter_contrib_nbextensions-0.5.0.dist-info/DESCRIPTION.rst
jupyter_contrib_nbextensions-0.5.0.dist-info/METADATA
jupyter_contrib_nbextensions-0.5.0.dist-info/RECORD
jupyter_contrib_nbextensions-0.5.0.dist-info/WHEEL
jupyter_contrib_nbextensions-0.5.0.dist-info/entry_points.txt
jupyter_contrib_nbextensions-0.5.0.dist-info/metadata.json
jupyter_contrib_nbextensions-0.5.0.dist-info/top_level.txt
