Metadata-Version: 1.1
Name: jupyter-contrib-nbextensions
Version: 0.5.0
Summary: A collection of Jupyter nbextensions.
Home-page: https://github.com/ipython-contrib/jupyter_contrib_nbextensions.git
Author: ipython-contrib and jupyter-contrib developers
Author-email: jupytercontrib@gmail.com
License: BSD
Download-URL: https://github.com/ipython-contrib/jupyter_contrib_nbextensions/tarball/0.5.0
Keywords: IPython,Jupyter,notebook
Platform: Any
Classifier: Development Status :: 1 - Planning
Classifier: Intended Audience :: End Users/Desktop
Classifier: Intended Audience :: Science/Research
Classifier: License :: OSI Approved :: BSD License
Classifier: Natural Language :: English
Classifier: Operating System :: OS Independent
Classifier: Programming Language :: JavaScript
Classifier: Programming Language :: Python
Classifier: Topic :: Utilities
